ks_ibkr_api/./.gitignore
ks_ibkr_api/./1.26.1
ks_ibkr_api/./AvailableAlgoParams.py
ks_ibkr_api/./ContractSamples.py
ks_ibkr_api/./FaAllocationSamples.py
ks_ibkr_api/./LICENSE.txt
ks_ibkr_api/./OrderSamples.py
ks_ibkr_api/./README.en.md
ks_ibkr_api/./README.md
ks_ibkr_api/./ScannerSubscriptionSamples.py
ks_ibkr_api/./__about__.py
ks_ibkr_api/./__init__.py
ks_ibkr_api/./base_manager.py
ks_ibkr_api/./constant.py
ks_ibkr_api/./contract_manager.py
ks_ibkr_api/./ib_api.py
ks_ibkr_api/./ks_ibkr_api.py
ks_ibkr_api/./order_manager.py
ks_ibkr_api/./position_manager.py
ks_ibkr_api/./pyproject.toml
ks_ibkr_api/./request_manager.py
ks_ibkr_api/./requirements.txt
ks_ibkr_api/./setup.py
ks_ibkr_api/./tick_manager.py
ks_ibkr_api/./ibapi/__init__.py
ks_ibkr_api/./ibapi/account_summary_tags.py
ks_ibkr_api/./ibapi/client.py
ks_ibkr_api/./ibapi/comm.py
ks_ibkr_api/./ibapi/commission_report.py
ks_ibkr_api/./ibapi/common.py
ks_ibkr_api/./ibapi/connection.py
ks_ibkr_api/./ibapi/contract.py
ks_ibkr_api/./ibapi/decoder.py
ks_ibkr_api/./ibapi/enum_implem.py
ks_ibkr_api/./ibapi/errors.py
ks_ibkr_api/./ibapi/execution.py
ks_ibkr_api/./ibapi/ibapi.pyproj
ks_ibkr_api/./ibapi/message.py
ks_ibkr_api/./ibapi/news.py
ks_ibkr_api/./ibapi/object_implem.py
ks_ibkr_api/./ibapi/order.py
ks_ibkr_api/./ibapi/order_condition.py
ks_ibkr_api/./ibapi/order_state.py
ks_ibkr_api/./ibapi/orderdecoder.py
ks_ibkr_api/./ibapi/reader.py
ks_ibkr_api/./ibapi/scanner.py
ks_ibkr_api/./ibapi/server_versions.py
ks_ibkr_api/./ibapi/softdollartier.py
ks_ibkr_api/./ibapi/tag_value.py
ks_ibkr_api/./ibapi/ticktype.py
ks_ibkr_api/./ibapi/utils.py
ks_ibkr_api/./ibapi/wrapper.py
ks_ibkr_api-0.0.29.dist-info/METADATA
ks_ibkr_api-0.0.29.dist-info/WHEEL
ks_ibkr_api-0.0.29.dist-info/licenses/LICENSE.txt
ks_ibkr_api-0.0.29.dist-info/RECORD
